extendedrandcrack/__init__.py
extendedrandcrack/extendedrandcrack.py
extendedrandcrack-1.0.0.dist-info/METADATA
extendedrandcrack-1.0.0.dist-info/WHEEL
extendedrandcrack-1.0.0.dist-info/top_level.txt
extendedrandcrack-1.0.0.dist-info/RECORD
