Metadata-Version: 2.4
Name: extendedrandcrack
Version: 1.0.0
Summary: Predict Python's random module outputs, extended with 64-bit support and state rewind/advance
Home-page: https://github.com/tomek7667/ExtendedRandCrack
Author: tomek7667
Author-email: tomek7667@cyber-man.pl
License: MIT
Keywords: random,mersenne-twister,security,cryptography,prng,predictor,cracker,random-crack,python-random
Classifier: Development Status :: 5 - Production/Stable
Classifier: Intended Audience :: Developers
Classifier: Topic :: Security
Classifier: Topic :: Security :: Cryptography
Classifier: License :: OSI Approved :: MIT License
Classifier: Programming Language :: Python :: 3
Classifier: Programming Language :: Python :: 3.6
Classifier: Programming Language :: Python :: 3.7
Classifier: Programming Language :: Python :: 3.8
Classifier: Programming Language :: Python :: 3.9
Classifier: Programming Language :: Python :: 3.10
Classifier: Programming Language :: Python :: 3.11
Classifier: Programming Language :: Python :: Implementation :: CPython
Dynamic: author
Dynamic: author-email
Dynamic: classifier
Dynamic: description
Dynamic: description-content-type
Dynamic: home-page
Dynamic: keywords
Dynamic: license
Dynamic: summary
